{
  "experiences": {
    "en": [
      {
        "title": "Web Developer",
        "company": "Xcommerce",
        "period": "2022 - 2024",
        "description": [
          "Maintenance of CMS platform with Laravel and Vue.js",
          "Integration of RESTful APIs and implementation of backend features with Laravel",
          "Code refactoring",
          "Creation of new features both in the frontend and backend"
        ]
      },
      {
        "title": "Full Stack Developer",
        "company": "Freelance / Personal Projects",
        "period": "2022 - Present",
        "description": [
          "Built web applications using Angular and Spring Boot",
          "Applied object-oriented programming principles to design maintainable code",
          "Collaborated with clients to define requirements and deliver tailored solutions"
        ]
      }
    ],
    "es": [
      {
        "title": "Desarrollador Web",
        "company": "Xcommerce",
        "period": "2024 - Presente",
        "description": [
          "Mantenimiento de plataforma CMS con Laravel y Vue.js",
          "Integración de APIs RESTful e implementación de funcionalidades de backend con Laravel",
          "Refactorización de código",
          "Creación de nuevas funcionalidades que tanto en el frontend como en el backend"
        ]
      },
      {
        "title": "Desarrollador Full Stack",
        "company": "Freelance / Proyectos Personales",
        "period": "2022 - 2024",
        "description": [
          "Contrucción de aplicaciones web usando Angular y Spring Boot",
          "Aplicación de principios de programación orientada a objetos para diseñar código mantenible",
          "Colaboración con clientes para definir requisitos y entregar soluciones a medida"
        ]
      }
    ]
  }
}
